{
	"configurations" : 
	[
		{
			"directories" : 
			[
				{
					"build" : ".",
					"childIndexes" : 
					[
						1,
						2,
						4
					],
					"hasInstallRule" : true,
					"jsonFile" : "directory-.-Debug-d0094a50bb2071803777.json",
					"minimumCMakeVersion" : 
					{
						"string" : "3.16"
					},
					"projectIndex" : 0,
					"source" : ".",
					"targetIndexes" : 
					[
						7,
						8,
						10
					]
				},
				{
					"build" : "_deps/glad-build",
					"jsonFile" : "directory-_deps.glad-build-Debug-bab926935a71f833f66b.json",
					"minimumCMakeVersion" : 
					{
						"string" : "3.0"
					},
					"parentIndex" : 0,
					"projectIndex" : 1,
					"source" : "build/_deps/glad-src",
					"targetIndexes" : 
					[
						0,
						1
					]
				},
				{
					"build" : "_deps/glfw-build",
					"childIndexes" : 
					[
						3
					],
					"hasInstallRule" : true,
					"jsonFile" : "directory-_deps.glfw-build-Debug-a1c60d883a6996f35b21.json",
					"minimumCMakeVersion" : 
					{
						"string" : "3.4"
					},
					"parentIndex" : 0,
					"projectIndex" : 2,
					"source" : "build/_deps/glfw-src",
					"targetIndexes" : 
					[
						9
					]
				},
				{
					"build" : "_deps/glfw-build/src",
					"hasInstallRule" : true,
					"jsonFile" : "directory-_deps.glfw-build.src-Debug-2f1e7a5892fce426449a.json",
					"minimumCMakeVersion" : 
					{
						"string" : "3.4"
					},
					"parentIndex" : 2,
					"projectIndex" : 2,
					"source" : "build/_deps/glfw-src/src",
					"targetIndexes" : 
					[
						2,
						11
					]
				},
				{
					"build" : "_deps/googletest-build",
					"childIndexes" : 
					[
						5
					],
					"hasInstallRule" : true,
					"jsonFile" : "directory-_deps.googletest-build-Debug-8b187651187085369010.json",
					"minimumCMakeVersion" : 
					{
						"string" : "3.5"
					},
					"parentIndex" : 0,
					"projectIndex" : 3,
					"source" : "build/_deps/googletest-src"
				},
				{
					"build" : "_deps/googletest-build/googlemock",
					"childIndexes" : 
					[
						6
					],
					"hasInstallRule" : true,
					"jsonFile" : "directory-_deps.googletest-build.googlemock-Debug-89d80ae5c830f53ad244.json",
					"minimumCMakeVersion" : 
					{
						"string" : "3.5"
					},
					"parentIndex" : 4,
					"projectIndex" : 4,
					"source" : "build/_deps/googletest-src/googlemock",
					"targetIndexes" : 
					[
						3,
						4
					]
				},
				{
					"build" : "_deps/googletest-build/googletest",
					"hasInstallRule" : true,
					"jsonFile" : "directory-_deps.googletest-build.googletest-Debug-eecf1e1409abb0e6dee7.json",
					"minimumCMakeVersion" : 
					{
						"string" : "3.5"
					},
					"parentIndex" : 5,
					"projectIndex" : 5,
					"source" : "build/_deps/googletest-src/googletest",
					"targetIndexes" : 
					[
						5,
						6
					]
				}
			],
			"name" : "Debug",
			"projects" : 
			[
				{
					"childIndexes" : 
					[
						1,
						2,
						3
					],
					"directoryIndexes" : 
					[
						0
					],
					"name" : "triangle_intersections",
					"targetIndexes" : 
					[
						7,
						8,
						10
					]
				},
				{
					"directoryIndexes" : 
					[
						1
					],
					"name" : "GLAD",
					"parentIndex" : 0,
					"targetIndexes" : 
					[
						0,
						1
					]
				},
				{
					"directoryIndexes" : 
					[
						2,
						3
					],
					"name" : "GLFW",
					"parentIndex" : 0,
					"targetIndexes" : 
					[
						2,
						9,
						11
					]
				},
				{
					"childIndexes" : 
					[
						4
					],
					"directoryIndexes" : 
					[
						4
					],
					"name" : "googletest-distribution",
					"parentIndex" : 0
				},
				{
					"childIndexes" : 
					[
						5
					],
					"directoryIndexes" : 
					[
						5
					],
					"name" : "gmock",
					"parentIndex" : 3,
					"targetIndexes" : 
					[
						3,
						4
					]
				},
				{
					"directoryIndexes" : 
					[
						6
					],
					"name" : "gtest",
					"parentIndex" : 4,
					"targetIndexes" : 
					[
						5,
						6
					]
				}
			],
			"targets" : 
			[
				{
					"directoryIndex" : 1,
					"id" : "glad::@f022c46af7fd79d63a94",
					"jsonFile" : "target-glad-Debug-ef54d276f0bfcc5d2317.json",
					"name" : "glad",
					"projectIndex" : 1
				},
				{
					"directoryIndex" : 1,
					"id" : "glad-generate-files::@f022c46af7fd79d63a94",
					"jsonFile" : "target-glad-generate-files-Debug-6e0615dbe1f2ff3bb92d.json",
					"name" : "glad-generate-files",
					"projectIndex" : 1
				},
				{
					"directoryIndex" : 3,
					"id" : "glfw::@fa9f4482d3a2b070f206",
					"jsonFile" : "target-glfw-Debug-310709f7b044082b6783.json",
					"name" : "glfw",
					"projectIndex" : 2
				},
				{
					"directoryIndex" : 5,
					"id" : "gmock::@0f7bb11d64f3678238c7",
					"jsonFile" : "target-gmock-Debug-883f17b0114344b7d70c.json",
					"name" : "gmock",
					"projectIndex" : 4
				},
				{
					"directoryIndex" : 5,
					"id" : "gmock_main::@0f7bb11d64f3678238c7",
					"jsonFile" : "target-gmock_main-Debug-47f8155ba4aafdcb8bbf.json",
					"name" : "gmock_main",
					"projectIndex" : 4
				},
				{
					"directoryIndex" : 6,
					"id" : "gtest::@1ea2dfc0605fe3ab2a3f",
					"jsonFile" : "target-gtest-Debug-e44f4b3924f2e0c93fa9.json",
					"name" : "gtest",
					"projectIndex" : 5
				},
				{
					"directoryIndex" : 6,
					"id" : "gtest_main::@1ea2dfc0605fe3ab2a3f",
					"jsonFile" : "target-gtest_main-Debug-f2d146514dbadd5b845c.json",
					"name" : "gtest_main",
					"projectIndex" : 5
				},
				{
					"directoryIndex" : 0,
					"id" : "imgui::@6890427a1f51a3e7e1df",
					"jsonFile" : "target-imgui-Debug-c752caa66b3cb18a8321.json",
					"name" : "imgui",
					"projectIndex" : 0
				},
				{
					"directoryIndex" : 0,
					"id" : "triangle_intersection::@6890427a1f51a3e7e1df",
					"jsonFile" : "target-triangle_intersection-Debug-64b71e2b2dde9b2bf3fb.json",
					"name" : "triangle_intersection",
					"projectIndex" : 0
				},
				{
					"directoryIndex" : 2,
					"id" : "uninstall::@369fad943889a5ec39c8",
					"jsonFile" : "target-uninstall-Debug-b6052d957b9f13eb5c64.json",
					"name" : "uninstall",
					"projectIndex" : 2
				},
				{
					"directoryIndex" : 0,
					"id" : "unit_tests::@6890427a1f51a3e7e1df",
					"jsonFile" : "target-unit_tests-Debug-6f2587fec88e46a077c4.json",
					"name" : "unit_tests",
					"projectIndex" : 0
				},
				{
					"directoryIndex" : 3,
					"id" : "update_mappings::@fa9f4482d3a2b070f206",
					"jsonFile" : "target-update_mappings-Debug-2c717f0c41a16d189b92.json",
					"name" : "update_mappings",
					"projectIndex" : 2
				}
			]
		}
	],
	"kind" : "codemodel",
	"paths" : 
	{
		"build" : "C:/Users/user/tria_project/triangle_intersections/build",
		"source" : "C:/Users/user/tria_project/triangle_intersections"
	},
	"version" : 
	{
		"major" : 2,
		"minor" : 5
	}
}
